<gpx version="1"><trk>
<trkpt lat="10.032747287414557" lon="57.06306471411133" />
<trkpt lat="10.032445787414556" lon="57.06306471411133" />
<trkpt lat="10.032144287414555" lon="57.06306471411133" />
<trkpt lat="10.031842787414554" lon="57.06306471411133" />
<trkpt lat="10.031239787414552" lon="57.063366214111326" />
<trkpt lat="10.031541287414553" lon="57.063366214111326" />
<trkpt lat="10.031842787414554" lon="57.063366214111326" />
<trkpt lat="10.032144287414555" lon="57.063366214111326" />
<trkpt lat="10.032445787414556" lon="57.063366214111326" />
<trkpt lat="10.032747287414557" lon="57.063366214111326" />
<trkpt lat="10.033048787414558" lon="57.063366214111326" />
<trkpt lat="10.032445787414556" lon="57.063667714111325" />
<trkpt lat="10.032144287414555" lon="57.063667714111325" />
<trkpt lat="10.031842787414554" lon="57.063667714111325" />
<trkpt lat="10.031541287414553" lon="57.063667714111325" />
<trkpt lat="10.031239787414552" lon="57.063667714111325" />
<trkpt lat="10.030938287414552" lon="57.063667714111325" />
<trkpt lat="10.031239787414552" lon="57.063969214111324" />
<trkpt lat="10.031541287414553" lon="57.063969214111324" />
<trkpt lat="10.031842787414554" lon="57.063969214111324" />
<trkpt lat="10.032144287414555" lon="57.063969214111324" />
</trk></gpx>